antlr/__init__.py
antlr/xDroneLexer.py
antlr/xDroneParser.py
antlr/xDroneParserListener.py
antlr/xDroneParserVisitor.py
cmdline/__init__.py
cmdline/xdrone.py
libs/__init__.py
libs/TelloEduSwarmSearch/__init__.py
libs/TelloEduSwarmSearch/comms_manager.py
libs/TelloEduSwarmSearch/emergency_stop.py
libs/TelloEduSwarmSearch/fly_tello.py
libs/TelloEduSwarmSearch/tello.py
tests/__init__.py
tests/command_converters_tests/__init__.py
tests/command_converters_tests/test_dji_tello_drone_executor.py
tests/command_converters_tests/test_dji_tello_edu_drone_executor.py
tests/command_converters_tests/test_simulation_converter.py
tests/commands_generator_tests/__init__.py
tests/commands_generator_tests/test_generate_commands.py
tests/compiler_tests/__init__.py
tests/compiler_tests/test_declare_assign.py
tests/compiler_tests/test_expr_operations.py
tests/compiler_tests/test_flow_control.py
tests/compiler_tests/test_function_definition_and_call.py
tests/compiler_tests/test_list_vector.py
tests/compiler_tests/test_movement_commands.py
tests/compiler_tests/test_multiple_drones.py
tests/compiler_tests/compiler_utils_tests/__init__.py
tests/compiler_tests/compiler_utils_tests/test_drones.py
tests/compiler_tests/compiler_utils_tests/test_expressions.py
tests/compiler_tests/compiler_utils_tests/test_functions.py
tests/compiler_tests/compiler_utils_tests/test_symbol_table.py
tests/compiler_tests/compiler_utils_tests/test_types.py
tests/config_parser_tests/__init__.py
tests/config_parser_tests/test_config_parser.py
tests/safety_checker_tests/__init__.py
tests/safety_checker_tests/test_boundary_checker.py
tests/safety_checker_tests/test_collision_checker.py
tests/shared_data_types_tests/__init__.py
tests/shared_data_types_tests/test_boundary_config.py
tests/shared_data_types_tests/test_collision_config.py
tests/shared_data_types_tests/test_commands.py
tests/shared_data_types_tests/test_drone_config.py
tests/shared_data_types_tests/test_state.py
tests/state_updater_tests/__init__.py
xdrone-0.2.9.dist-info/METADATA
xdrone-0.2.9.dist-info/WHEEL
xdrone-0.2.9.dist-info/entry_points.txt
xdrone-0.2.9.dist-info/top_level.txt
xdrone-0.2.9.dist-info/RECORD
