Metadata-Version: 2.1
Name: xdrone
Version: 0.2.9
Summary: xDrone Language Server
Home-page: https://github.com/xDrone-DSL/xDroneLanguageServer
Author: Kai Zhu
License: MIT
Platform: UNKNOWN
Classifier: License :: OSI Approved :: MIT License
Classifier: Programming Language :: Python :: 3
Classifier: Programming Language :: Python :: 3.7
Requires-Dist: click
Requires-Dist: antlr4-python3-runtime
Requires-Dist: netifaces
Requires-Dist: netaddr
Requires-Dist: scipy
Requires-Dist: matplotlib
Requires-Dist: tabulate
